Planky/__init__.py
Planky/plankyClient.py
Planky/plankyData.py
Planky/plankyDecorators.py
Planky/plankyHandler.py
Planky/plankyProtocol.py
Planky/plankyReader.py
Planky/plankyServer.py
Planky/plankyWriter.py
Planky/base/__init__.py
Planky/base/client.py
Planky/base/handler.py
Planky/base/listener.py
Planky/base/protocol.py
Planky/base/reader.py
Planky/base/server.py
Planky/base/storage.py
Planky/base/writer.py
Planky/base/data/__init__.py
Planky/base/data/data.py
Planky/base/data/event.py
Planky/base/data/message.py
Planky/base/data/storageItem.py
Planky/decorators/__init__.py
Planky/decorators/onConnect.py
Planky/decorators/onDisconnect.py
Planky/decorators/onMessage.py
Planky/decorators/onPing.py
Planky/events/__init__.py
Planky/events/connectEvent.py
Planky/events/disconnectEvent.py
Planky/events/messageEvent.py
Planky/events/pingEvent.py
Planky/listeners/__init__.py
Planky/listeners/onConnect.py
Planky/listeners/onDisconnect.py
Planky/listeners/onMessage.py
Planky/listeners/onPing.py
Planky/messages/__init__.py
Planky/messages/parsedMessage.py
Planky/messages/pingMessage.py
Planky/messages/rawMessage.py
planky-0.1.dist-info/METADATA
planky-0.1.dist-info/WHEEL
planky-0.1.dist-info/top_level.txt
planky-0.1.dist-info/RECORD
