Metadata-Version: 2.1
Name: planky
Version: 0.1
Summary: Planky is is an easy-to-use and highly customizable tool for building your own tcp/tls server.
Author-email: BonePolk <bonepolk@gmail.com>
Project-URL: Homepage, https://github.com/BonePolk/Planky
Project-URL: Issues, https://github.com/BonePolk/Planky/issues
Classifier: Programming Language :: Python :: 3
Classifier: License :: OSI Approved :: MIT License
Classifier: Operating System :: OS Independent
Requires-Python: >=3.8
